{
  "annual": {
    "VND": 20509.75
  },
  "base": "USD",
  "provenance": [
    {
      "currencies": [
        "EUR",
        "GBP",
        "JPY"
      ],
      "from": "2011-01-03",
      "provider": "frankfurter",
      "series": "daily",
      "to": "2011-12-30"
    },
    {
      "currencies": [
        "VND"
      ],
      "provider": "world_bank",
      "series": "annual",
      "year": 2011
    }
  ],
  "providers": [
    {
      "fetched_at": "2026-05-11",
      "id": "frankfurter",
      "label": "Frankfurter (ECB) daily reference rates",
      "status": "ok"
    },
    {
      "fetched_at": "2026-05-11",
      "id": "world_bank",
      "label": "World Bank PA.NUS.FCRF",
      "status": "ok"
    }
  ],
  "rates": {
    "2011-01-03": {
      "EUR": 0.74918,
      "GBP": 0.64527,
      "JPY": 81.44
    },
    "2011-01-04": {
      "EUR": 0.7451,
      "GBP": 0.63986,
      "JPY": 82.11
    },
    "2011-01-05": {
      "EUR": 0.75683,
      "GBP": 0.64202,
      "JPY": 82.28
    },
    "2011-01-06": {
      "EUR": 0.76388,
      "GBP": 0.6451,
      "JPY": 83.2
    },
    "2011-01-07": {
      "EUR": 0.77155,
      "GBP": 0.64679,
      "JPY": 83.55
    },
    "2011-01-10": {
      "EUR": 0.77501,
      "GBP": 0.64466,
      "JPY": 83.06
    },
    "2011-01-11": {
      "EUR": 0.77232,
      "GBP": 0.64249,
      "JPY": 83.11
    },
    "2011-01-12": {
      "EUR": 0.77083,
      "GBP": 0.64099,
      "JPY": 83.38
    },
    "2011-01-13": {
      "EUR": 0.75763,
      "GBP": 0.63319,
      "JPY": 82.96
    },
    "2011-01-14": {
      "EUR": 0.74912,
      "GBP": 0.63091,
      "JPY": 82.94
    },
    "2011-01-17": {
      "EUR": 0.75126,
      "GBP": 0.62813,
      "JPY": 82.57
    },
    "2011-01-18": {
      "EUR": 0.74789,
      "GBP": 0.62497,
      "JPY": 82.48
    },
    "2011-01-19": {
      "EUR": 0.74041,
      "GBP": 0.62439,
      "JPY": 82.07
    },
    "2011-01-20": {
      "EUR": 0.74228,
      "GBP": 0.62619,
      "JPY": 82.34
    },
    "2011-01-21": {
      "EUR": 0.73959,
      "GBP": 0.62736,
      "JPY": 82.74
    },
    "2011-01-24": {
      "EUR": 0.73687,
      "GBP": 0.62751,
      "JPY": 82.87
    },
    "2011-01-25": {
      "EUR": 0.73551,
      "GBP": 0.63401,
      "JPY": 82.44
    },
    "2011-01-26": {
      "EUR": 0.73094,
      "GBP": 0.63098,
      "JPY": 82.21
    },
    "2011-01-27": {
      "EUR": 0.72908,
      "GBP": 0.62668,
      "JPY": 83.04
    },
    "2011-01-28": {
      "EUR": 0.72939,
      "GBP": 0.62794,
      "JPY": 82.25
    },
    "2011-01-31": {
      "EUR": 0.73035,
      "GBP": 0.62876,
      "JPY": 82.16
    },
    "2011-02-01": {
      "EUR": 0.72701,
      "GBP": 0.62057,
      "JPY": 81.56
    },
    "2011-02-02": {
      "EUR": 0.72448,
      "GBP": 0.61718,
      "JPY": 81.4
    },
    "2011-02-03": {
      "EUR": 0.72754,
      "GBP": 0.61742,
      "JPY": 81.82
    },
    "2011-02-04": {
      "EUR": 0.73362,
      "GBP": 0.62152,
      "JPY": 81.74
    },
    "2011-02-07": {
      "EUR": 0.73784,
      "GBP": 0.61994,
      "JPY": 82.28
    },
    "2011-02-08": {
      "EUR": 0.73341,
      "GBP": 0.62237,
      "JPY": 82.21
    },
    "2011-02-09": {
      "EUR": 0.73276,
      "GBP": 0.62285,
      "JPY": 82.55
    },
    "2011-02-10": {
      "EUR": 0.73508,
      "GBP": 0.6232,
      "JPY": 82.85
    },
    "2011-02-11": {
      "EUR": 0.73943,
      "GBP": 0.62533,
      "JPY": 83.56
    },
    "2011-02-14": {
      "EUR": 0.74405,
      "GBP": 0.625,
      "JPY": 83.44
    },
    "2011-02-15": {
      "EUR": 0.74019,
      "GBP": 0.61991,
      "JPY": 83.8
    },
    "2011-02-16": {
      "EUR": 0.74019,
      "GBP": 0.62317,
      "JPY": 83.73
    },
    "2011-02-17": {
      "EUR": 0.73746,
      "GBP": 0.62013,
      "JPY": 83.62
    },
    "2011-02-18": {
      "EUR": 0.73384,
      "GBP": 0.61606,
      "JPY": 83.38
    },
    "2011-02-21": {
      "EUR": 0.73164,
      "GBP": 0.6164,
      "JPY": 83.17
    },
    "2011-02-22": {
      "EUR": 0.73169,
      "GBP": 0.61889,
      "JPY": 83.14
    },
    "2011-02-23": {
      "EUR": 0.72828,
      "GBP": 0.61605,
      "JPY": 82.8
    },
    "2011-02-24": {
      "EUR": 0.72606,
      "GBP": 0.61809,
      "JPY": 81.82
    },
    "2011-02-25": {
      "EUR": 0.72664,
      "GBP": 0.62149,
      "JPY": 81.76
    },
    "2011-02-28": {
      "EUR": 0.72286,
      "GBP": 0.61645,
      "JPY": 81.87
    },
    "2011-03-01": {
      "EUR": 0.72333,
      "GBP": 0.61439,
      "JPY": 82.02
    },
    "2011-03-02": {
      "EUR": 0.72417,
      "GBP": 0.61395,
      "JPY": 82.07
    },
    "2011-03-03": {
      "EUR": 0.72202,
      "GBP": 0.61466,
      "JPY": 81.9
    },
    "2011-03-04": {
      "EUR": 0.71649,
      "GBP": 0.61478,
      "JPY": 82.85
    },
    "2011-03-07": {
      "EUR": 0.71286,
      "GBP": 0.61377,
      "JPY": 82.09
    },
    "2011-03-08": {
      "EUR": 0.71953,
      "GBP": 0.61915,
      "JPY": 82.49
    },
    "2011-03-09": {
      "EUR": 0.71798,
      "GBP": 0.61674,
      "JPY": 82.67
    },
    "2011-03-10": {
      "EUR": 0.72375,
      "GBP": 0.61992,
      "JPY": 83.07
    },
    "2011-03-11": {
      "EUR": 0.72606,
      "GBP": 0.62528,
      "JPY": 82.22
    },
    "2011-03-14": {
      "EUR": 0.71695,
      "GBP": 0.62081,
      "JPY": 81.85
    },
    "2011-03-15": {
      "EUR": 0.72025,
      "GBP": 0.62475,
      "JPY": 80.95
    },
    "2011-03-16": {
      "EUR": 0.71679,
      "GBP": 0.62168,
      "JPY": 80.59
    },
    "2011-03-17": {
      "EUR": 0.71408,
      "GBP": 0.61943,
      "JPY": 78.849
    },
    "2011-03-18": {
      "EUR": 0.70771,
      "GBP": 0.6184,
      "JPY": 81.16
    },
    "2011-03-21": {
      "EUR": 0.70452,
      "GBP": 0.61413,
      "JPY": 81.05
    },
    "2011-03-22": {
      "EUR": 0.70368,
      "GBP": 0.61065,
      "JPY": 81.03
    },
    "2011-03-23": {
      "EUR": 0.70741,
      "GBP": 0.61538,
      "JPY": 80.94
    },
    "2011-03-24": {
      "EUR": 0.70781,
      "GBP": 0.6187,
      "JPY": 80.93
    },
    "2011-03-25": {
      "EUR": 0.70847,
      "GBP": 0.62189,
      "JPY": 81.17
    },
    "2011-03-28": {
      "EUR": 0.71266,
      "GBP": 0.62589,
      "JPY": 81.66
    },
    "2011-03-29": {
      "EUR": 0.71093,
      "GBP": 0.62665,
      "JPY": 82.18
    },
    "2011-03-30": {
      "EUR": 0.70972,
      "GBP": 0.62378,
      "JPY": 83.04
    },
    "2011-03-31": {
      "EUR": 0.70388,
      "GBP": 0.62202,
      "JPY": 82.78
    },
    "2011-04-01": {
      "EUR": 0.70716,
      "GBP": 0.62336,
      "JPY": 83.84
    },
    "2011-04-04": {
      "EUR": 0.70225,
      "GBP": 0.61864,
      "JPY": 83.96
    },
    "2011-04-05": {
      "EUR": 0.70592,
      "GBP": 0.61616,
      "JPY": 84.29
    },
    "2011-04-06": {
      "EUR": 0.6993,
      "GBP": 0.61364,
      "JPY": 85.19
    },
    "2011-04-07": {
      "EUR": 0.70013,
      "GBP": 0.61325,
      "JPY": 85.21
    },
    "2011-04-08": {
      "EUR": 0.6944,
      "GBP": 0.61173,
      "JPY": 85.27
    },
    "2011-04-11": {
      "EUR": 0.69281,
      "GBP": 0.61217,
      "JPY": 84.7
    },
    "2011-04-12": {
      "EUR": 0.69109,
      "GBP": 0.61399,
      "JPY": 84.22
    },
    "2011-04-13": {
      "EUR": 0.68999,
      "GBP": 0.61395,
      "JPY": 84.07
    },
    "2011-04-14": {
      "EUR": 0.6944,
      "GBP": 0.6128,
      "JPY": 83.22
    },
    "2011-04-15": {
      "EUR": 0.69204,
      "GBP": 0.61163,
      "JPY": 83.3
    },
    "2011-04-18": {
      "EUR": 0.70053,
      "GBP": 0.61471,
      "JPY": 82.84
    },
    "2011-04-19": {
      "EUR": 0.6992,
      "GBP": 0.6139,
      "JPY": 82.67
    },
    "2011-04-20": {
      "EUR": 0.68894,
      "GBP": 0.61089,
      "JPY": 82.76
    },
    "2011-04-21": {
      "EUR": 0.68568,
      "GBP": 0.60429,
      "JPY": 81.95
    },
    "2011-04-26": {
      "EUR": 0.68413,
      "GBP": 0.60693,
      "JPY": 81.71
    },
    "2011-04-27": {
      "EUR": 0.68176,
      "GBP": 0.60431,
      "JPY": 82.26
    },
    "2011-04-28": {
      "EUR": 0.67595,
      "GBP": 0.60078,
      "JPY": 81.77
    },
    "2011-04-29": {
      "EUR": 0.67295,
      "GBP": 0.60007,
      "JPY": 81.2
    },
    "2011-05-02": {
      "EUR": 0.67399,
      "GBP": 0.59931,
      "JPY": 81.45
    },
    "2011-05-03": {
      "EUR": 0.67659,
      "GBP": 0.60687,
      "JPY": 80.76
    },
    "2011-05-04": {
      "EUR": 0.67195,
      "GBP": 0.60469,
      "JPY": 81.05
    },
    "2011-05-05": {
      "EUR": 0.67504,
      "GBP": 0.60662,
      "JPY": 79.789
    },
    "2011-05-06": {
      "EUR": 0.68961,
      "GBP": 0.60954,
      "JPY": 80.34
    },
    "2011-05-09": {
      "EUR": 0.69459,
      "GBP": 0.61072,
      "JPY": 80.77
    },
    "2011-05-10": {
      "EUR": 0.69648,
      "GBP": 0.61144,
      "JPY": 80.6
    },
    "2011-05-11": {
      "EUR": 0.69652,
      "GBP": 0.6065,
      "JPY": 81.12
    },
    "2011-05-12": {
      "EUR": 0.70656,
      "GBP": 0.61482,
      "JPY": 80.93
    },
    "2011-05-13": {
      "EUR": 0.70028,
      "GBP": 0.61481,
      "JPY": 80.76
    },
    "2011-05-16": {
      "EUR": 0.70706,
      "GBP": 0.61691,
      "JPY": 80.85
    },
    "2011-05-17": {
      "EUR": 0.70567,
      "GBP": 0.61598,
      "JPY": 81.64
    },
    "2011-05-18": {
      "EUR": 0.70289,
      "GBP": 0.619,
      "JPY": 81.15
    },
    "2011-05-19": {
      "EUR": 0.70102,
      "GBP": 0.61781,
      "JPY": 81.9
    },
    "2011-05-20": {
      "EUR": 0.7024,
      "GBP": 0.61604,
      "JPY": 81.67
    },
    "2011-05-23": {
      "EUR": 0.71327,
      "GBP": 0.62036,
      "JPY": 81.8
    },
    "2011-05-24": {
      "EUR": 0.70977,
      "GBP": 0.61953,
      "JPY": 81.94
    },
    "2011-05-25": {
      "EUR": 0.71078,
      "GBP": 0.61639,
      "JPY": 82.07
    },
    "2011-05-26": {
      "EUR": 0.70582,
      "GBP": 0.613,
      "JPY": 81.84
    },
    "2011-05-27": {
      "EUR": 0.70102,
      "GBP": 0.60768,
      "JPY": 81.11
    },
    "2011-05-30": {
      "EUR": 0.70067,
      "GBP": 0.60755,
      "JPY": 80.83
    },
    "2011-05-31": {
      "EUR": 0.69517,
      "GBP": 0.60622,
      "JPY": 81.49
    },
    "2011-06-01": {
      "EUR": 0.69406,
      "GBP": 0.60872,
      "JPY": 81.28
    },
    "2011-06-02": {
      "EUR": 0.69156,
      "GBP": 0.61062,
      "JPY": 80.64
    },
    "2011-06-03": {
      "EUR": 0.69023,
      "GBP": 0.61258,
      "JPY": 80.68
    },
    "2011-06-06": {
      "EUR": 0.68512,
      "GBP": 0.60996,
      "JPY": 80.19
    },
    "2011-06-07": {
      "EUR": 0.6825,
      "GBP": 0.6091,
      "JPY": 80.23
    },
    "2011-06-08": {
      "EUR": 0.68456,
      "GBP": 0.61124,
      "JPY": 79.819
    },
    "2011-06-09": {
      "EUR": 0.68428,
      "GBP": 0.60859,
      "JPY": 79.964
    },
    "2011-06-10": {
      "EUR": 0.69032,
      "GBP": 0.61328,
      "JPY": 80.08
    },
    "2011-06-13": {
      "EUR": 0.69667,
      "GBP": 0.61349,
      "JPY": 80.39
    },
    "2011-06-14": {
      "EUR": 0.69214,
      "GBP": 0.60977,
      "JPY": 80.23
    },
    "2011-06-15": {
      "EUR": 0.69969,
      "GBP": 0.61552,
      "JPY": 80.84
    },
    "2011-06-16": {
      "EUR": 0.70982,
      "GBP": 0.62131,
      "JPY": 80.66
    },
    "2011-06-17": {
      "EUR": 0.70077,
      "GBP": 0.6185,
      "JPY": 80.39
    },
    "2011-06-20": {
      "EUR": 0.70249,
      "GBP": 0.61784,
      "JPY": 80.25
    },
    "2011-06-21": {
      "EUR": 0.69575,
      "GBP": 0.61692,
      "JPY": 80.15
    },
    "2011-06-22": {
      "EUR": 0.69459,
      "GBP": 0.62034,
      "JPY": 80.13
    },
    "2011-06-23": {
      "EUR": 0.70363,
      "GBP": 0.62595,
      "JPY": 80.62
    },
    "2011-06-24": {
      "EUR": 0.70323,
      "GBP": 0.62486,
      "JPY": 80.21
    },
    "2011-06-27": {
      "EUR": 0.70398,
      "GBP": 0.62633,
      "JPY": 80.77
    },
    "2011-06-28": {
      "EUR": 0.70121,
      "GBP": 0.62702,
      "JPY": 80.86
    },
    "2011-06-29": {
      "EUR": 0.69324,
      "GBP": 0.62378,
      "JPY": 81.06
    },
    "2011-06-30": {
      "EUR": 0.6919,
      "GBP": 0.62447,
      "JPY": 80.43
    },
    "2011-07-01": {
      "EUR": 0.69023,
      "GBP": 0.62465,
      "JPY": 80.7
    },
    "2011-07-04": {
      "EUR": 0.68966,
      "GBP": 0.62172,
      "JPY": 80.77
    },
    "2011-07-05": {
      "EUR": 0.69152,
      "GBP": 0.62126,
      "JPY": 81.07
    },
    "2011-07-06": {
      "EUR": 0.69842,
      "GBP": 0.62498,
      "JPY": 81.04
    },
    "2011-07-07": {
      "EUR": 0.7019,
      "GBP": 0.62617,
      "JPY": 81.17
    },
    "2011-07-08": {
      "EUR": 0.70215,
      "GBP": 0.62716,
      "JPY": 81.44
    },
    "2011-07-11": {
      "EUR": 0.71144,
      "GBP": 0.62657,
      "JPY": 80.51
    },
    "2011-07-12": {
      "EUR": 0.71556,
      "GBP": 0.63159,
      "JPY": 79.678
    },
    "2011-07-13": {
      "EUR": 0.71058,
      "GBP": 0.62695,
      "JPY": 79.336
    },
    "2011-07-14": {
      "EUR": 0.70413,
      "GBP": 0.6203,
      "JPY": 79.031
    },
    "2011-07-15": {
      "EUR": 0.70691,
      "GBP": 0.62032,
      "JPY": 79.153
    },
    "2011-07-18": {
      "EUR": 0.712,
      "GBP": 0.62168,
      "JPY": 79.103
    },
    "2011-07-19": {
      "EUR": 0.70621,
      "GBP": 0.62069,
      "JPY": 78.934
    },
    "2011-07-20": {
      "EUR": 0.70388,
      "GBP": 0.61987,
      "JPY": 78.87
    },
    "2011-07-21": {
      "EUR": 0.70314,
      "GBP": 0.61785,
      "JPY": 78.815
    },
    "2011-07-22": {
      "EUR": 0.69488,
      "GBP": 0.61337,
      "JPY": 78.403
    },
    "2011-07-25": {
      "EUR": 0.69541,
      "GBP": 0.6137,
      "JPY": 78.206
    },
    "2011-07-26": {
      "EUR": 0.69104,
      "GBP": 0.60974,
      "JPY": 78.101
    },
    "2011-07-27": {
      "EUR": 0.69223,
      "GBP": 0.61131,
      "JPY": 77.849
    },
    "2011-07-28": {
      "EUR": 0.70126,
      "GBP": 0.61283,
      "JPY": 77.742
    },
    "2011-07-29": {
      "EUR": 0.70126,
      "GBP": 0.6135,
      "JPY": 77.553
    },
    "2011-08-01": {
      "EUR": 0.69372,
      "GBP": 0.61016,
      "JPY": 76.892
    },
    "2011-08-02": {
      "EUR": 0.70572,
      "GBP": 0.61524,
      "JPY": 77.354
    },
    "2011-08-03": {
      "EUR": 0.6993,
      "GBP": 0.61017,
      "JPY": 77.049
    },
    "2011-08-04": {
      "EUR": 0.70279,
      "GBP": 0.61245,
      "JPY": 79.584
    },
    "2011-08-05": {
      "EUR": 0.70646,
      "GBP": 0.61395,
      "JPY": 78.594
    },
    "2011-08-08": {
      "EUR": 0.70299,
      "GBP": 0.61097,
      "JPY": 77.884
    },
    "2011-08-09": {
      "EUR": 0.70092,
      "GBP": 0.61197,
      "JPY": 77.269
    },
    "2011-08-10": {
      "EUR": 0.69604,
      "GBP": 0.61551,
      "JPY": 76.453
    },
    "2011-08-11": {
      "EUR": 0.70706,
      "GBP": 0.61918,
      "JPY": 76.568
    },
    "2011-08-12": {
      "EUR": 0.70175,
      "GBP": 0.61498,
      "JPY": 76.54
    },
    "2011-08-15": {
      "EUR": 0.69886,
      "GBP": 0.6129,
      "JPY": 76.784
    },
    "2011-08-16": {
      "EUR": 0.69638,
      "GBP": 0.61177,
      "JPY": 76.685
    },
    "2011-08-17": {
      "EUR": 0.69075,
      "GBP": 0.6062,
      "JPY": 76.514
    },
    "2011-08-18": {
      "EUR": 0.69594,
      "GBP": 0.60589,
      "JPY": 76.609
    },
    "2011-08-19": {
      "EUR": 0.69517,
      "GBP": 0.60455,
      "JPY": 76.469
    },
    "2011-08-22": {
      "EUR": 0.69382,
      "GBP": 0.60615,
      "JPY": 76.771
    },
    "2011-08-23": {
      "EUR": 0.69147,
      "GBP": 0.60573,
      "JPY": 76.559
    },
    "2011-08-24": {
      "EUR": 0.69286,
      "GBP": 0.6077,
      "JPY": 76.568
    },
    "2011-08-25": {
      "EUR": 0.69329,
      "GBP": 0.61093,
      "JPY": 77.17
    },
    "2011-08-26": {
      "EUR": 0.69435,
      "GBP": 0.61495,
      "JPY": 76.663
    },
    "2011-08-29": {
      "EUR": 0.69027,
      "GBP": 0.61062,
      "JPY": 76.655
    },
    "2011-08-30": {
      "EUR": 0.69435,
      "GBP": 0.61356,
      "JPY": 76.76
    },
    "2011-08-31": {
      "EUR": 0.69204,
      "GBP": 0.61287,
      "JPY": 76.505
    },
    "2011-09-01": {
      "EUR": 0.70004,
      "GBP": 0.61687,
      "JPY": 77.06
    },
    "2011-09-02": {
      "EUR": 0.70151,
      "GBP": 0.61656,
      "JPY": 76.857
    },
    "2011-09-05": {
      "EUR": 0.70791,
      "GBP": 0.6195,
      "JPY": 76.851
    },
    "2011-09-06": {
      "EUR": 0.70927,
      "GBP": 0.6221,
      "JPY": 77.374
    },
    "2011-09-07": {
      "EUR": 0.71245,
      "GBP": 0.62553,
      "JPY": 77.216
    },
    "2011-09-08": {
      "EUR": 0.71205,
      "GBP": 0.62425,
      "JPY": 77.193
    },
    "2011-09-09": {
      "EUR": 0.72375,
      "GBP": 0.62669,
      "JPY": 77.788
    },
    "2011-09-12": {
      "EUR": 0.73228,
      "GBP": 0.62987,
      "JPY": 77.124
    },
    "2011-09-13": {
      "EUR": 0.73287,
      "GBP": 0.63258,
      "JPY": 76.959
    },
    "2011-09-14": {
      "EUR": 0.72839,
      "GBP": 0.63333,
      "JPY": 76.83
    },
    "2011-09-15": {
      "EUR": 0.7249,
      "GBP": 0.6328,
      "JPY": 76.6
    },
    "2011-09-16": {
      "EUR": 0.72674,
      "GBP": 0.6335,
      "JPY": 76.744
    },
    "2011-09-19": {
      "EUR": 0.73308,
      "GBP": 0.63639,
      "JPY": 76.695
    },
    "2011-09-20": {
      "EUR": 0.72939,
      "GBP": 0.63625,
      "JPY": 76.528
    },
    "2011-09-21": {
      "EUR": 0.73335,
      "GBP": 0.64029,
      "JPY": 76.32
    },
    "2011-09-22": {
      "EUR": 0.7436,
      "GBP": 0.64935,
      "JPY": 76.286
    },
    "2011-09-23": {
      "EUR": 0.7446,
      "GBP": 0.64955,
      "JPY": 76.188
    },
    "2011-09-26": {
      "EUR": 0.74074,
      "GBP": 0.64415,
      "JPY": 76.333
    },
    "2011-09-27": {
      "EUR": 0.73643,
      "GBP": 0.64055,
      "JPY": 76.464
    },
    "2011-09-28": {
      "EUR": 0.73362,
      "GBP": 0.63953,
      "JPY": 76.458
    },
    "2011-09-29": {
      "EUR": 0.73448,
      "GBP": 0.63948,
      "JPY": 76.724
    },
    "2011-09-30": {
      "EUR": 0.74058,
      "GBP": 0.64182,
      "JPY": 76.864
    },
    "2011-10-03": {
      "EUR": 0.75036,
      "GBP": 0.64501,
      "JPY": 76.829
    },
    "2011-10-04": {
      "EUR": 0.75867,
      "GBP": 0.6498,
      "JPY": 76.686
    },
    "2011-10-05": {
      "EUR": 0.74979,
      "GBP": 0.64707,
      "JPY": 76.666
    },
    "2011-10-06": {
      "EUR": 0.75364,
      "GBP": 0.65325,
      "JPY": 76.773
    },
    "2011-10-07": {
      "EUR": 0.74438,
      "GBP": 0.64374,
      "JPY": 76.686
    },
    "2011-10-10": {
      "EUR": 0.73567,
      "GBP": 0.63923,
      "JPY": 76.701
    },
    "2011-10-11": {
      "EUR": 0.73492,
      "GBP": 0.63952,
      "JPY": 76.622
    },
    "2011-10-12": {
      "EUR": 0.72643,
      "GBP": 0.63588,
      "JPY": 76.834
    },
    "2011-10-13": {
      "EUR": 0.72849,
      "GBP": 0.63805,
      "JPY": 76.841
    },
    "2011-10-14": {
      "EUR": 0.72427,
      "GBP": 0.63359,
      "JPY": 77.077
    },
    "2011-10-17": {
      "EUR": 0.7259,
      "GBP": 0.63444,
      "JPY": 77.258
    },
    "2011-10-18": {
      "EUR": 0.73121,
      "GBP": 0.6363,
      "JPY": 76.755
    },
    "2011-10-19": {
      "EUR": 0.72317,
      "GBP": 0.63274,
      "JPY": 76.793
    },
    "2011-10-20": {
      "EUR": 0.72427,
      "GBP": 0.63374,
      "JPY": 76.823
    },
    "2011-10-21": {
      "EUR": 0.72474,
      "GBP": 0.6289,
      "JPY": 76.692
    },
    "2011-10-24": {
      "EUR": 0.72171,
      "GBP": 0.62724,
      "JPY": 76.104
    },
    "2011-10-25": {
      "EUR": 0.71849,
      "GBP": 0.62516,
      "JPY": 76.146
    },
    "2011-10-26": {
      "EUR": 0.71803,
      "GBP": 0.62605,
      "JPY": 75.874
    },
    "2011-10-27": {
      "EUR": 0.71235,
      "GBP": 0.62423,
      "JPY": 75.787
    },
    "2011-10-28": {
      "EUR": 0.70621,
      "GBP": 0.62101,
      "JPY": 75.77
    },
    "2011-10-31": {
      "EUR": 0.71423,
      "GBP": 0.6236,
      "JPY": 78.009
    },
    "2011-11-01": {
      "EUR": 0.73384,
      "GBP": 0.62754,
      "JPY": 78.212
    },
    "2011-11-02": {
      "EUR": 0.72417,
      "GBP": 0.62416,
      "JPY": 78.051
    },
    "2011-11-03": {
      "EUR": 0.72606,
      "GBP": 0.6239,
      "JPY": 77.928
    },
    "2011-11-04": {
      "EUR": 0.72606,
      "GBP": 0.62532,
      "JPY": 78.088
    },
    "2011-11-07": {
      "EUR": 0.7277,
      "GBP": 0.62331,
      "JPY": 78.082
    },
    "2011-11-08": {
      "EUR": 0.72527,
      "GBP": 0.62232,
      "JPY": 77.974
    },
    "2011-11-09": {
      "EUR": 0.73351,
      "GBP": 0.62631,
      "JPY": 77.723
    },
    "2011-11-10": {
      "EUR": 0.73443,
      "GBP": 0.62673,
      "JPY": 77.6
    },
    "2011-11-11": {
      "EUR": 0.7326,
      "GBP": 0.62769,
      "JPY": 77.355
    },
    "2011-11-14": {
      "EUR": 0.73212,
      "GBP": 0.62713,
      "JPY": 77.004
    },
    "2011-11-15": {
      "EUR": 0.73899,
      "GBP": 0.63069,
      "JPY": 76.973
    },
    "2011-11-16": {
      "EUR": 0.74162,
      "GBP": 0.63357,
      "JPY": 76.958
    },
    "2011-11-17": {
      "EUR": 0.74184,
      "GBP": 0.63353,
      "JPY": 76.973
    },
    "2011-11-18": {
      "EUR": 0.73659,
      "GBP": 0.63203,
      "JPY": 76.65
    },
    "2011-11-21": {
      "EUR": 0.74305,
      "GBP": 0.63903,
      "JPY": 76.861
    },
    "2011-11-22": {
      "EUR": 0.73883,
      "GBP": 0.6396,
      "JPY": 76.949
    },
    "2011-11-23": {
      "EUR": 0.74699,
      "GBP": 0.64264,
      "JPY": 77.217
    },
    "2011-11-24": {
      "EUR": 0.74778,
      "GBP": 0.64354,
      "JPY": 77.073
    },
    "2011-11-25": {
      "EUR": 0.75592,
      "GBP": 0.64695,
      "JPY": 77.549
    },
    "2011-11-28": {
      "EUR": 0.74918,
      "GBP": 0.64294,
      "JPY": 77.779
    },
    "2011-11-29": {
      "EUR": 0.74985,
      "GBP": 0.64011,
      "JPY": 77.849
    },
    "2011-11-30": {
      "EUR": 0.74527,
      "GBP": 0.6378,
      "JPY": 77.508
    },
    "2011-12-01": {
      "EUR": 0.74118,
      "GBP": 0.63675,
      "JPY": 77.705
    },
    "2011-12-02": {
      "EUR": 0.74014,
      "GBP": 0.63667,
      "JPY": 77.899
    },
    "2011-12-05": {
      "EUR": 0.74394,
      "GBP": 0.63923,
      "JPY": 77.972
    },
    "2011-12-06": {
      "EUR": 0.7466,
      "GBP": 0.6395,
      "JPY": 77.759
    },
    "2011-12-07": {
      "EUR": 0.74755,
      "GBP": 0.64099,
      "JPY": 77.738
    },
    "2011-12-08": {
      "EUR": 0.74571,
      "GBP": 0.63594,
      "JPY": 77.345
    },
    "2011-12-09": {
      "EUR": 0.74716,
      "GBP": 0.63744,
      "JPY": 77.667
    },
    "2011-12-12": {
      "EUR": 0.75466,
      "GBP": 0.63995,
      "JPY": 77.821
    },
    "2011-12-13": {
      "EUR": 0.75867,
      "GBP": 0.64202,
      "JPY": 77.839
    },
    "2011-12-14": {
      "EUR": 0.76965,
      "GBP": 0.64573,
      "JPY": 78.073
    },
    "2011-12-15": {
      "EUR": 0.76811,
      "GBP": 0.64471,
      "JPY": 77.809
    },
    "2011-12-16": {
      "EUR": 0.76546,
      "GBP": 0.64341,
      "JPY": 77.848
    },
    "2011-12-19": {
      "EUR": 0.76693,
      "GBP": 0.64407,
      "JPY": 77.859
    },
    "2011-12-20": {
      "EUR": 0.76488,
      "GBP": 0.64005,
      "JPY": 77.926
    },
    "2011-12-21": {
      "EUR": 0.76605,
      "GBP": 0.63758,
      "JPY": 77.877
    },
    "2011-12-22": {
      "EUR": 0.76646,
      "GBP": 0.63808,
      "JPY": 78.125
    },
    "2011-12-23": {
      "EUR": 0.76587,
      "GBP": 0.63805,
      "JPY": 78.065
    },
    "2011-12-27": {
      "EUR": 0.76517,
      "GBP": 0.63777,
      "JPY": 77.856
    },
    "2011-12-28": {
      "EUR": 0.76488,
      "GBP": 0.63806,
      "JPY": 77.643
    },
    "2011-12-29": {
      "EUR": 0.77586,
      "GBP": 0.64862,
      "JPY": 77.772
    },
    "2011-12-30": {
      "EUR": 0.77286,
      "GBP": 0.64557,
      "JPY": 77.44
    }
  },
  "schema_version": 3,
  "year": 2011
}
